Workbook

Sheet Dashboard
B2: 📊 PAINEL DO MÊS GABRIEL & BEATRIZ
B3: ="Mês de referência: "&TEXT('Meu Mês'!F3,"mmmm/yyyy")&" • os números atualizam sozinhos conforme vocês anotam os gastos" -> Mês de referência: outubro/yyyy • os números atualizam sozinhos conforme vocês anotam os gastos
B5: 💰 QUANTO TEMOS | C5: 🧾 JÁ GASTAMOS | D5: 🏦 VAI SOBRAR | E5: 📅 POR DIA* | F5: 💸 % GASTO | G5: 🛟 % LIVRE
B6: ='Meu Mês'!E13 -> 8700 | C6: ='Meu Mês'!F13 -> 4240 | D6: ='Meu Mês'!G13 -> 4460 | E6: ='Meu Mês'!H13 -> 178.4 | F6: =IF('Meu Mês'!E13=0,0,'Meu Mês'!F13/'Meu Mês'!E13) -> 0.48735632 | G6: =IF('Meu Mês'!E13=0,0,1-'Meu Mês'!F13/'Meu Mês'!E13) -> 0.51264368
B7: * por dia = o que vai sobrar ÷ dias que faltam até o fim do mês
B9: 🏷️ GASTOS POR CATEGORIA
B10: Categoria | C10: Gasto (R$) | D10: % do total
B11: Moradia | C11: =SUMIF('Meu Mês'!G18:G200,B11,'Meu Mês'!F18:F200) -> 1500 | D11: =IF('Meu Mês'!F13=0,0,C11/'Meu Mês'!F13) -> 0.35377358
B12: Alimentação | C12: =SUMIF('Meu Mês'!G18:G200,B12,'Meu Mês'!F18:F200) -> 0 | D12: =IF('Meu Mês'!F13=0,0,C12/'Meu Mês'!F13) -> 0
B13: Transporte | C13: =SUMIF('Meu Mês'!G18:G200,B13,'Meu Mês'!F18:F200) -> 500 | D13: =IF('Meu Mês'!F13=0,0,C13/'Meu Mês'!F13) -> 0.11792453
B14: Saúde | C14: =SUMIF('Meu Mês'!G18:G200,B14,'Meu Mês'!F18:F200) -> 0 | D14: =IF('Meu Mês'!F13=0,0,C14/'Meu Mês'!F13) -> 0
B15: Lazer | C15: =SUMIF('Meu Mês'!G18:G200,B15,'Meu Mês'!F18:F200) -> 200 | D15: =IF('Meu Mês'!F13=0,0,C15/'Meu Mês'!F13) -> 0.047169811
B16: Educação | C16: =SUMIF('Meu Mês'!G18:G200,B16,'Meu Mês'!F18:F200) -> 250 | D16: =IF('Meu Mês'!F13=0,0,C16/'Meu Mês'!F13) -> 0.058962264
B17: Contas (luz/água/internet) | C17: =SUMIF('Meu Mês'!G18:G200,B17,'Meu Mês'!F18:F200) -> 140 | D17: =IF('Meu Mês'!F13=0,0,C17/'Meu Mês'!F13) -> 0.033018868
B18: Mercado | C18: =SUMIF('Meu Mês'!G18:G200,B18,'Meu Mês'!F18:F200) -> 0 | D18: =IF('Meu Mês'!F13=0,0,C18/'Meu Mês'!F13) -> 0
B19: Assinaturas | C19: =SUMIF('Meu Mês'!G18:G200,B19,'Meu Mês'!F18:F200) -> 0 | D19: =IF('Meu Mês'!F13=0,0,C19/'Meu Mês'!F13) -> 0
B20: Filhos/Pets | C20: =SUMIF('Meu Mês'!G18:G200,B20,'Meu Mês'!F18:F200) -> 0 | D20: =IF('Meu Mês'!F13=0,0,C20/'Meu Mês'!F13) -> 0
B21: Vestuário | C21: =SUMIF('Meu Mês'!G18:G200,B21,'Meu Mês'!F18:F200) -> 0 | D21: =IF('Meu Mês'!F13=0,0,C21/'Meu Mês'!F13) -> 0
B22: Outros | C22: =SUMIF('Meu Mês'!G18:G200,B22,'Meu Mês'!F18:F200) -> 0 | D22: =IF('Meu Mês'!F13=0,0,C22/'Meu Mês'!F13) -> 0
B23: TOTAL | C23: =SUM(C11:C22) -> 2590 | D23: =SUM(D11:D22) -> 0.61084906
B25: 🙋 GASTOS POR PESSOA
B26: Gabriel | C26: =SUMIF('Meu Mês'!H18:H200,B26,'Meu Mês'!F18:F200) -> 4240
B27: Beatriz | C27: =SUMIF('Meu Mês'!H18:H200,B27,'Meu Mês'!F18:F200) -> 0
B28: Os dois | C28: =SUMIF('Meu Mês'!H18:H200,B28,'Meu Mês'!F18:F200) -> 0
B30: =IF('Meu Mês'!G13<0,"⚠️ Atenção: vocês já gastaram MAIS do que têm no mês!",IF('Meu Mês'!F13/'Meu Mês'!E13>0.8,"⚠️ Cuidado: já passou de 80% do que têm!","✅ Tudo certo! Os gastos estão dentro do planejado.")) -> ✅ Tudo certo! Os gastos estão dentro do planejado.

Sheet Contas Fixas
E1: GASTOS DO MÊS GABRIEL & BEATRIZ
E3: Mês: | F3: 46296 | G3: (troque a data para outro mês, ex.: 01/10/2026)
E5: 💰 QUANTO TEMOS — preencha aqui as entradas
E6: Salário Gabriel | H6: 3500
E7: Salário Beatriz | H7: 4000
E8: Freelance / renda extra (preencha se houver) | H8: 1200
E9: TOTAL QUE TEMOS NO MÊS | H9: =SUM(H6:H8) -> 8700
E11: 📊 RESUMO - atualiza sozinho
E12: QUANTO TEMOS | F12: JÁ GASTAMOS | G12: VAI SOBRAR | H12: PODEMOS GASTAR POR DIA*
E13: =H9 -> 8700 | F13: =SUM(F18:F200) -> 9230 | G13: =H9-SUM(F18:F200) -> -530 | H13: =(H9-SUM(F18:F200))/MAX(1,DAY(EOMONTH(F3,0))-DAY(TODAY())+1) -> -21.2
E14: * valor por dia = o que vai sobrar ÷ dias que faltam até o fim do mês
E16: 🧾 GASTOS: anote cada gasto numa linha (data, descrição, categoria, quem pagou, valor)
E17: Data | F17: Valor (R$) | G17: Categoria | H17: Quem pagou | I17: Descrição
F18: 1500 | G18: Moradia | H18: Gabriel | I18: Aluguel
F19: 400 | G19: Contas (luz/água/internet) | H19: Gabriel | I19: Luz
F20: 300 | G20: Contas (luz/água/internet) | H20: Gabriel | I20: Água
F21: 1600 | G21: Transporte | H21: Gabriel | I21: Carro
F22: 500 | G22: Transporte | H22: Gabriel | I22: Gasolina
F23: 2000 | G23: Compras | H23: Gabriel | I23: Mercado(VR + DINHEIRO)
F24: 400 | G24: Educação | H24: Gabriel | I24: Faculdades
F25: 700 | G25: Cartão | H25: Gabriel | I25: Cartões em geral
F26: 300 | G26: Vestuário | H26: Gabriel | I26: Roupas / Acessórios
F27: 180 | G27: Contas (luz/água/internet) | H27: Gabriel | I27: Internet móvel + tv + internet fixa
F28: 100 | G28: Transporte | H28: Gabriel | I28: Manutenção Carro
F29: 400 | G29: Saúde | H29: Gabriel | I29: Academia
... F32: 400 | G32: Beleza | H32: Gabriel | I32: Corte de cabelo, unhas, dep...

Sheet Meu Mês
E1: GASTOS DO MÊS GABRIEL & BEATRIZ
E3: Mês: | F3: 46296 | G3: (troque a data para outro mês, ex.: 01/10/2026)
E5: 💰 QUANTO TEMOS — preencha aqui as entradas
E6: Salário Gabriel | H6: 3500
E7: Salário Beatriz | H7: 4000
E8: Freelance / renda extra (preencha se houver) | H8: 1200
E9: TOTAL QUE TEMOS NO MÊS | H9: =SUM(H6:H8) -> 8700
E11: 📊 RESUMO - atualiza sozinho
E12: QUANTO TEMOS | F12: JÁ GASTAMOS | G12: VAI SOBRAR | H12: PODEMOS GASTAR POR DIA*
E13: =H9 -> 8700 | F13: =SUM(F18:F200) -> 4240 | G13: =H9-SUM(F18:F200) -> 4460 | H13: =(H9-SUM(F18:F200))/MAX(1,DAY(EOMONTH(F3,0))-DAY(TODAY())+1) -> 178.4
E14: * valor por dia = o que vai sobrar ÷ dias que faltam até o fim do mês
E16: 🧾 GASTOS: anote cada gasto numa linha (data, descrição, categoria, quem pagou, valor)
E17: Data | F17: Valor (R$) | G17: Categoria | H17: Quem pagou | I17: Descrição
E18: 46295 | F18: 1500 | G18: Moradia | H18: Gabriel | I18: Aluguel
G19: Contas (luz/água/internet) | H19: Gabriel | I19: Luz
G20: Contas (luz/água/internet) | H20: Gabriel | I20: Água
F21: 400 | G21: Transporte | H21: Gabriel | I21: Carro
F22: 100 | G22: Transporte | H22: Gabriel | I22: Gasolina
F23: 800 | G23: Compras | H23: Gabriel | I23: Mercado(VR + DINHEIRO)
F24: 250 | G24: Educação | H24: Gabriel | I24: Faculdades
F25: 850 | G25: Cartão | H25: Gabriel | I25: Cartões em geral
G26: Vestuário | H26: Gabriel | I26: Roupas / Acessórios
F27: 140 | G27: Contas (luz/água/internet) | H27: Gabriel | I27: Internet móvel + tv + internet fixa
G28: Transporte | H28: Gabriel | I28: Manutenção Carro
G29: Saúde | H29: Gabriel | I29: Academia
F30: 200 | G30: Lazer | H30: Gabriel | I30: IFood, saída etc...
G31: Saúde | H31: Gabriel | I31: Remédios
G32: Beleza | H32: Gabriel | I32: Corte de cabelo, unhas, dep...

Sheet Planilha1
H3: ESTIMATIVAS MENORES
H5: Valor (R$) | I5: Categoria | J5: Quem pagou | K5: Descrição
H6: 1500 | I6: Moradia | J6: Gabriel | K6: Aluguel
H7: 300 | I7: Contas (luz/água/internet) | J7: Gabriel | K7: Luz
H8: 200 | I8: Contas (luz/água/internet) | J8: Gabriel | K8: Água
H9: 1600 | I9: Transporte | J9: Gabriel | K9: Carro
H10: 500 | I10: Transporte | J10: Gabriel | K10: Gasolina
H11: 1200 | I11: Compras | J11: Gabriel | K11: Mercado(VR + DINHEIRO)
H12: 380 | I12: Educação | J12: Gabriel | K12: Faculdades
H13: 400 | I13: Cartão | J13: Gabriel | K13: Cartões em geral
H14: 150 | I14: Vestuário | J14: Gabriel | K14: Roupas / Acessórios
H15: 120 | I15: Contas (luz/água/internet) | J15: Gabriel | K15: Internet móvel + tv + internet fixa
H16: 100 | I16: Transporte | J16: Gabriel | K16: Manutenção Carro
H17: 320 | I17: Saúde | J17: Gabriel | K17: Academia
... H20: 400 | I20: Beleza | J20: Gabriel | K20: Corte de cabelo, unhas, dep...
